chaogate/__init__.py
chaogate/_nbdev.py
chaogate/core.py
chaogate/plotting.py
chaogate-0.0.1.dist-info/LICENSE
chaogate-0.0.1.dist-info/METADATA
chaogate-0.0.1.dist-info/WHEEL
chaogate-0.0.1.dist-info/entry_points.txt
chaogate-0.0.1.dist-info/top_level.txt
chaogate-0.0.1.dist-info/RECORD
